snap4frame/__init__.py
snap4frame/config.py
snap4frame/const.py
snap4frame/main.py
snap4frame/types.py
snap4frame/core/decoder.py
snap4frame/core/filters.py
snap4frame/core/hook.py
snap4frame/core/log.py
snap4frame/core/metaclass.py
snap4frame/core/store.py
snap4frame/core/types.py
snap4frame/core/handlers/__init__.py
snap4frame/core/handlers/event.py
snap4frame/core/handlers/exception.py
snap4frame/core/handlers/source.py
snap4frame/core/reports/__init__.py
snap4frame/core/reports/additional.py
snap4frame/core/reports/context.py
snap4frame/core/reports/interpreter.py
snap4frame/core/reports/machine.py
snap4frame/core/reports/packages.py
snap4frame/processor/__init__.py
snap4frame/processor/base.py
snap4frame/processor/kit.py
snap4frame-0.1.2.dist-info/METADATA
snap4frame-0.1.2.dist-info/WHEEL
snap4frame-0.1.2.dist-info/RECORD
