Metadata-Version: 2.3
Name: snap4frame
Version: 0.1.2
Summary: Creates a snapshot of the python program for later analysis
Author-email: Panaintescu Adrian Valentin <adrian.cert@gmail.com>
License: MIT License
Requires-Python: >=3.8
Requires-Dist: importlib-metadata>=7.0.1
Provides-Extra: dev
Requires-Dist: pre-commit>=3.5.0; extra == 'dev'
Requires-Dist: ruff>=0.3.7; extra == 'dev'
Requires-Dist: tox>=4.14.2; extra == 'dev'
Provides-Extra: msgspec
Requires-Dist: msgspec>=0.18.6; extra == 'msgspec'
Provides-Extra: requests
Requires-Dist: requests>=2.31.0; extra == 'requests'
